hatch_argparse_manpage/__about__.py
hatch_argparse_manpage/__init__.py
hatch_argparse_manpage/hooks.py
hatch_argparse_manpage/plugin.py
hatch_argparse_manpage/py.typed
hatch_argparse_manpage-1.0.0.dist-info/METADATA
hatch_argparse_manpage-1.0.0.dist-info/WHEEL
hatch_argparse_manpage-1.0.0.dist-info/entry_points.txt
hatch_argparse_manpage-1.0.0.dist-info/licenses/LICENSE.txt
hatch_argparse_manpage-1.0.0.dist-info/RECORD
