Metadata-Version: 2.3
Name: hatch-argparse-manpage
Version: 1.0.0
Summary: Hatch build hook plugin to generate manual pages
Project-URL: Documentation, https://github.com/damonlynch/hatch-argparse-manpage#readme
Project-URL: Issues, https://github.com/damonlynch/hatch-argparse-manpage/issues
Project-URL: Homepage, https://github.com/damonlynch/hatch-argparse-manpage
Author-email: Damon Lynch <damonlynch@gmail.com>
License-Expression: GPL-3.0-or-later
License-File: LICENSE.txt
Keywords: build,documentation,hatch,help,man page,manpage,manual page,plugin,typing
Classifier: Development Status :: 5 - Production/Stable
Classifier: Framework :: Hatch
Classifier: Programming Language :: Python
Classifier: Programming Language :: Python :: 3.8
Classifier: Programming Language :: Python :: 3.9
Classifier: Programming Language :: Python :: 3.10
Classifier: Programming Language :: Python :: 3.11
Classifier: Programming Language :: Python :: 3.12
Classifier: Programming Language :: Python :: Implementation :: CPython
Classifier: Programming Language :: Python :: Implementation :: PyPy
Classifier: Typing :: Typed
Requires-Python: >=3.8
Requires-Dist: argparse-manpage
Requires-Dist: rich
